{
  "tabPane": [
    {
      "title": "Driver",
      "autoPopulate": true,
      "autoPopulatePrefix": "",
      "widgetPane": {
        "gridSize": 64.0,
        "showGrid": true,
        "hgap": 16.0,
        "vgap": 16.0,
        "tiles": {
          "0,0": {
            "size": [
              10,
              6
            ],
            "content": {
              "_type": "Camera Stream",
              "_source0": "camera_server://limelight",
              "_title": "limelight",
              "Crosshair/Show crosshair": true,
              "Crosshair/Crosshair color": "#FFFFFFFF",
              "Controls/Show controls": true,
              "Controls/Rotation": "NONE",
              "compression": -1.0,
              "fps": -1,
              "imageWidth": 0,
              "imageHeight": 0
            }
          },
          "10,0": {
            "size": [
              3,
              1
            ],
            "content": {
              "_type": "Basic FMS Info",
              "_source0": "network_table:///FMSInfo",
              "_title": "FMSInfo"
            }
          }
        }
      }
    },
    {
      "title": "Drivetrain Tab",
      "autoPopulate": true,
      "autoPopulatePrefix": "network_table:///Shuffleboard/Drivetrain Tab/",
      "widgetPane": {
        "gridSize": 128.0,
        "showGrid": true,
        "hgap": 16.0,
        "vgap": 16.0,
        "tiles": {
          "0,0": {
            "size": [
              1,
              1
            ],
            "content": {
              "_type": "Text View",
              "_source0": "network_table:///Shuffleboard/Drivetrain Tab/Driving Constraint - Max",
              "_title": "Driving Constraint - Max"
            }
          },
          "1,0": {
            "size": [
              1,
              1
            ],
            "content": {
              "_type": "Text View",
              "_source0": "network_table:///Shuffleboard/Drivetrain Tab/hIntegratorMax",
              "_title": "hIntegratorMax"
            }
          },
          "2,0": {
            "size": [
              1,
              1
            ],
            "content": {
              "_type": "Text View",
              "_source0": "network_table:///Shuffleboard/Drivetrain Tab/hPosTolerance",
              "_title": "hPosTolerance"
            }
          },
          "3,0": {
            "size": [
              1,
              1
            ],
            "content": {
              "_type": "Text View",
              "_source0": "network_table:///Shuffleboard/Drivetrain Tab/Vision - Kd",
              "_title": "Vision - Kd"
            }
          },
          "4,0": {
            "size": [
              1,
              1
            ],
            "content": {
              "_type": "Text View",
              "_source0": "network_table:///Shuffleboard/Drivetrain Tab/Vision - Ki",
              "_title": "Vision - Ki"
            }
          },
          "5,0": {
            "size": [
              1,
              1
            ],
            "content": {
              "_type": "Text View",
              "_source0": "network_table:///Shuffleboard/Drivetrain Tab/Vision - Kp",
              "_title": "Vision - Kp"
            }
          },
          "6,0": {
            "size": [
              1,
              1
            ],
            "content": {
              "_type": "Text View",
              "_source0": "network_table:///Shuffleboard/Drivetrain Tab/Heading Constraint - Min",
              "_title": "Heading Constraint - Min"
            }
          },
          "7,0": {
            "size": [
              1,
              1
            ],
            "content": {
              "_type": "Text View",
              "_source0": "network_table:///Shuffleboard/Drivetrain Tab/Vision Constraint - Max",
              "_title": "Vision Constraint - Max"
            }
          },
          "8,0": {
            "size": [
              1,
              1
            ],
            "content": {
              "_type": "Text View",
              "_source0": "network_table:///Shuffleboard/Drivetrain Tab/Vision Constrraint - Min",
              "_title": "Vision Constrraint - Min"
            }
          },
          "9,0": {
            "size": [
              1,
              1
            ],
            "content": {
              "_type": "Text View",
              "_source0": "network_table:///Shuffleboard/Drivetrain Tab/Driving Constraint - Min",
              "_title": "Driving Constraint - Min"
            }
          },
          "0,1": {
            "size": [
              1,
              1
            ],
            "content": {
              "_type": "Text View",
              "_source0": "network_table:///Shuffleboard/Drivetrain Tab/hIntegratorMin",
              "_title": "hIntegratorMin"
            }
          },
          "1,1": {
            "size": [
              1,
              1
            ],
            "content": {
              "_type": "Text View",
              "_source0": "network_table:///Shuffleboard/Drivetrain Tab/number",
              "_title": "number"
            }
          },
          "2,1": {
            "size": [
              1,
              1
            ],
            "content": {
              "_type": "Text View",
              "_source0": "network_table:///Shuffleboard/Drivetrain Tab/Driving - Kd",
              "_title": "Driving - Kd"
            }
          },
          "3,1": {
            "size": [
              1,
              1
            ],
            "content": {
              "_type": "Text View",
              "_source0": "network_table:///Shuffleboard/Drivetrain Tab/Driving - Ki",
              "_title": "Driving - Ki"
            }
          },
          "4,1": {
            "size": [
              1,
              1
            ],
            "content": {
              "_type": "Text View",
              "_source0": "network_table:///Shuffleboard/Drivetrain Tab/x",
              "_title": "x"
            }
          },
          "5,1": {
            "size": [
              1,
              1
            ],
            "content": {
              "_type": "Text View",
              "_source0": "network_table:///Shuffleboard/Drivetrain Tab/Driving - Kp",
              "_title": "Driving - Kp"
            }
          },
          "6,1": {
            "size": [
              1,
              1
            ],
            "content": {
              "_type": "Text View",
              "_source0": "network_table:///Shuffleboard/Drivetrain Tab/Heading - Kd",
              "_title": "Heading - Kd"
            }
          },
          "7,1": {
            "size": [
              1,
              1
            ],
            "content": {
              "_type": "Text View",
              "_source0": "network_table:///Shuffleboard/Drivetrain Tab/Heading - Ki",
              "_title": "Heading - Ki"
            }
          },
          "8,1": {
            "size": [
              1,
              1
            ],
            "content": {
              "_type": "Text View",
              "_source0": "network_table:///Shuffleboard/Drivetrain Tab/Heading - Kp",
              "_title": "Heading - Kp"
            }
          },
          "9,1": {
            "size": [
              1,
              1
            ],
            "content": {
              "_type": "Text View",
              "_source0": "network_table:///Shuffleboard/Drivetrain Tab/hVTolerance",
              "_title": "hVTolerance"
            }
          },
          "0,2": {
            "size": [
              1,
              1
            ],
            "content": {
              "_type": "Text View",
              "_source0": "network_table:///Shuffleboard/Drivetrain Tab/Vision Constraint - Min",
              "_title": "Vision Constraint - Min"
            }
          },
          "1,2": {
            "size": [
              5,
              1
            ],
            "content": {
              "_type": "Text View",
              "_source0": "network_table:///Shuffleboard/Drivetrain Tab/Heading Constraint - max",
              "_title": "Heading Constraint - max"
            }
          }
        }
      }
    }
  ],
  "windowGeometry": {
    "x": -7.199999809265137,
    "y": -7.199999809265137,
    "width": 1550.4000244140625,
    "height": 838.4000244140625
  }
}